[
  {
    "icon": "fas fa-home",
    "title": "Início",
    "path": "dashboard"
  },
  {
    "icon": "far fa-calendar-alt",
    "title": "Agenda",
    "path": "calendar"
  },
  {
    "icon": "fas fa-hand-holding-usd",
    "title": "Orçamentos",
    "path": "budgets"
  },
  {
    "icon": "fas fa-file-alt",
    "title": "Estoque",
    "path": "stock"
  },
  {
    "icon": "fas fa-shipping-fast",
    "title": "Fornecedores",
    "path": "provider"
  },
  {
    "icon": "far fa-address-book",
    "title": "Cadastro de Clientes",
    "path": "customer"
  },
  {
    "icon": "far fa-address-card",
    "title": "Cadastro de Funcionários",
    "path": "employees"
  }
]
